astronomer_starship/__init__.py
astronomer_starship/common.py
astronomer_starship/eslint.config.js
astronomer_starship/index.html
astronomer_starship/starship.py
astronomer_starship/starship_api.py
astronomer_starship/vite.config.js
astronomer_starship/_af2/__init__.py
astronomer_starship/_af2/starship.py
astronomer_starship/_af2/starship_api.py
astronomer_starship/_af2/starship_compatability.py
astronomer_starship/_af3/__init__.py
astronomer_starship/_af3/starship.py
astronomer_starship/_af3/starship_api.py
astronomer_starship/_af3/starship_compatability.py
astronomer_starship/compat/__init__.py
astronomer_starship/compat/starship_compatability.py
astronomer_starship/providers/__init__.py
astronomer_starship/providers/starship/__init__.py
astronomer_starship/providers/starship/hooks/__init__.py
astronomer_starship/providers/starship/hooks/starship.py
astronomer_starship/providers/starship/operators/__init__.py
astronomer_starship/providers/starship/operators/starship.py
astronomer_starship/static/index.html
astronomer_starship/static/assets/ConnectionsPage.js
astronomer_starship/static/assets/DAGHistoryPage.js
astronomer_starship/static/assets/EnvVarsPage.js
astronomer_starship/static/assets/HiddenValue.js
astronomer_starship/static/assets/MigrateButton.js
astronomer_starship/static/assets/PageLoading.js
astronomer_starship/static/assets/PoolsPage.js
astronomer_starship/static/assets/ProgressSummary.js
astronomer_starship/static/assets/SetupPage.js
astronomer_starship/static/assets/TelescopePage.js
astronomer_starship/static/assets/VariablesPage.js
astronomer_starship/static/assets/chakra.js
astronomer_starship/static/assets/http.js
astronomer_starship/static/assets/icons.js
astronomer_starship/static/assets/index.css
astronomer_starship/static/assets/index.esm.js
astronomer_starship/static/assets/index.js
astronomer_starship/static/assets/react-core.js
astronomer_starship/static/assets/router.js
astronomer_starship/static/assets/table.js
astronomer_starship-2.8.3.dist-info/licenses/LICENSE
astronomer_starship-2.8.3.dist-info/METADATA
astronomer_starship-2.8.3.dist-info/WHEEL
astronomer_starship-2.8.3.dist-info/entry_points.txt
astronomer_starship-2.8.3.dist-info/top_level.txt
astronomer_starship-2.8.3.dist-info/RECORD
