Metadata-Version: 2.4
Name: astronomer-starship
Version: 2.8.3
Summary: Migrations to Astro
Author-email: Fritz Davenport <fritz@astronomer.io>, CETA Team <ceta@astronomer.io>, Astronomer <humans@astronomer.io>
License: PROPRIETARY
Project-URL: Homepage, https://astronomer.io
Project-URL: Source, https://github.com/astronomer/starship/
Classifier: Development Status :: 5 - Production/Stable
Classifier: Framework :: Apache Airflow
Classifier: Intended Audience :: Developers
Classifier: Programming Language :: Python :: 3.6
Classifier: Programming Language :: Python :: 3.7
Classifier: Programming Language :: Python :: 3.8
Classifier: Programming Language :: Python :: 3.9
Classifier: Programming Language :: Python :: 3.10
Classifier: Programming Language :: Python :: 3.11
Classifier: Programming Language :: Python :: 3.12
Requires-Python: >=3.6
License-File: LICENSE
Provides-Extra: provider
Requires-Dist: apache-airflow-providers-http; extra == "provider"
Provides-Extra: dev
Requires-Dist: twine; extra == "dev"
Requires-Dist: build; extra == "dev"
Requires-Dist: apache-airflow<3.2; extra == "dev"
Requires-Dist: pytest>=7; extra == "dev"
Requires-Dist: pytest-cov>=4.0; extra == "dev"
Requires-Dist: pytest-integration>=0.2; extra == "dev"
Requires-Dist: pytest-sugar>=0.9; extra == "dev"
Requires-Dist: docker>=6; extra == "dev"
Requires-Dist: mkdocs; extra == "dev"
Requires-Dist: mkdocs-material; extra == "dev"
Requires-Dist: mkdocstrings[python]; extra == "dev"
Requires-Dist: pygments; extra == "dev"
Dynamic: license-file
